{
    "id": 185204850,
    "name": "SpectrumScaleTools",
    "full_name": "IBM/SpectrumScaleTools",
    "org_name": "International Business Machines",
    "org_id": 1459110,
    "created_at": "2019-05-06T13:42:16",
    "pushed_at": "2023-03-10T07:34:02",
    "updated_at": "2022-11-09T09:41:46",
    "isFork": false,
    "forks": 5,
    "forks_count": 5,
    "has_downloads": true,
    "has_issues": true,
    "has_pages": false,
    "has_projects": true,
    "has_wiki": true,
    "homepage": null,
    "language": "Python",
    "open_issues": 0,
    "open_issues_count": 0,
    "size": 179,
    "stargazers_count": 15,
    "subscribers_count": 17,
    "watchers": 15,
    "watchers_count": 15,
    "first_commit": "2019-05-06T13:42:17",
    "last_commit": "2023-03-10T07:34:02",
    "branches_count": 1,
    "commit_comments_count": 0,
    "commits_count": 27,
    "countributors_count": 4,
    "downloads_count": 0,
    "events_count": 4,
    "issues_count": 0,
    "labels_count": 8,
    "milestones_count": 0,
    "PR_count": 0,
    "open_PR_count": 0,
    "readme_size": 2622,
    "release_count": 0,
    "topic_count": 4,
    "15_commits": 0,
    "16_commits": 0,
    "17_commits": 0,
    "18_commits": 0,
    "19_commits": 10,
    "20_commits": 11,
    "21_commits": 1,
    "22_commits": 3,
    "15_committer_num": 0,
    "16_committer_num": 0,
    "17_committer_num": 0,
    "18_committer_num": 0,
    "19_committer_num": 2,
    "20_committer_num": 1,
    "21_committer_num": 1,
    "22_committer_num": 2
}{
    "stargazer_date": {
        "7355037": "2019-08-01T06:46:33",
        "549284": "2020-05-11T21:26:45",
        "10786638": "2020-05-22T20:02:03",
        "3853794": "2020-06-19T14:21:47",
        "857275": "2020-07-08T14:08:54",
        "16475976": "2020-09-30T18:20:50",
        "6817407": "2020-12-08T22:18:23",
        "12758003": "2021-01-12T01:49:09",
        "78974161": "2021-02-24T15:26:42",
        "6956866": "2022-01-10T05:22:56",
        "678607": "2022-04-06T05:18:42",
        "459082": "2022-04-20T00:30:51",
        "7008670": "2022-06-28T09:49:37",
        "117267100": "2022-11-03T10:34:01"
    }
}[
    {
        "GHA": {}
    },
    {
        "Travis": []
    },
    {
        "CircleCI": []
    },
    {
        "AppVeyor": []
    },
    {
        "Azure": []
    },
    {
        "GitLab": []
    },
    {
        "Jenkins": []
    }
]