{
    "id": 371601459,
    "name": "app-modernization-coexistence-layer",
    "full_name": "IBM/app-modernization-coexistence-layer",
    "org_name": "International Business Machines",
    "org_id": 1459110,
    "created_at": "2021-05-28T06:23:31",
    "pushed_at": "2021-07-09T04:42:48",
    "updated_at": "2022-11-17T11:47:19",
    "isFork": false,
    "forks": 2,
    "forks_count": 2,
    "has_downloads": true,
    "has_issues": true,
    "has_pages": false,
    "has_projects": true,
    "has_wiki": true,
    "homepage": null,
    "language": "Java",
    "open_issues": 0,
    "open_issues_count": 0,
    "size": 21348,
    "stargazers_count": 2,
    "subscribers_count": 6,
    "watchers": 2,
    "watchers_count": 2,
    "first_commit": "2021-05-28T06:23:32",
    "last_commit": "2021-07-09T04:42:48",
    "branches_count": 1,
    "commit_comments_count": 0,
    "commits_count": 77,
    "countributors_count": 5,
    "downloads_count": 0,
    "events_count": 0,
    "issues_count": 0,
    "labels_count": 9,
    "milestones_count": 0,
    "PR_count": 9,
    "open_PR_count": 0,
    "readme_size": 23280,
    "release_count": 0,
    "topic_count": 0,
    "15_commits": 0,
    "16_commits": 0,
    "17_commits": 0,
    "18_commits": 0,
    "19_commits": 0,
    "20_commits": 0,
    "21_commits": 77,
    "22_commits": 0,
    "15_committer_num": 0,
    "16_committer_num": 0,
    "17_committer_num": 0,
    "18_committer_num": 0,
    "19_committer_num": 0,
    "20_committer_num": 0,
    "21_committer_num": 5,
    "22_committer_num": 0
}{
    "stargazer_date": {
        "563146": "2021-07-12T01:16:33",
        "68863248": "2022-01-16T20:16:09"
    }
}[
    {
        "GHA": {}
    },
    {
        "Travis": []
    },
    {
        "CircleCI": []
    },
    {
        "AppVeyor": []
    },
    {
        "Azure": []
    },
    {
        "GitLab": []
    },
    {
        "Jenkins": []
    }
]