{
    "id": 108418225,
    "name": "ns3-rmcat",
    "full_name": "cisco/ns3-rmcat",
    "org_name": "Cisco Systems",
    "org_id": 1376999,
    "created_at": "2017-10-26T13:53:07",
    "pushed_at": "2021-04-15T15:55:35",
    "updated_at": "2023-01-13T22:54:11",
    "isFork": false,
    "forks": 25,
    "forks_count": 25,
    "has_downloads": true,
    "has_issues": true,
    "has_pages": false,
    "has_projects": true,
    "has_wiki": true,
    "homepage": null,
    "language": "C++",
    "open_issues": 1,
    "open_issues_count": 1,
    "size": 134,
    "stargazers_count": 43,
    "subscribers_count": 13,
    "watchers": 43,
    "watchers_count": 43,
    "first_commit": "2017-11-14T21:20:26",
    "last_commit": "2020-09-16T19:16:02",
    "branches_count": 2,
    "commit_comments_count": 0,
    "commits_count": 41,
    "countributors_count": 3,
    "downloads_count": 0,
    "events_count": 1,
    "issues_count": 1,
    "labels_count": 8,
    "milestones_count": 0,
    "PR_count": 11,
    "open_PR_count": 0,
    "readme_size": 8121,
    "release_count": 0,
    "topic_count": 0,
    "15_commits": 0,
    "16_commits": 0,
    "17_commits": 6,
    "18_commits": 22,
    "19_commits": 2,
    "20_commits": 11,
    "21_commits": 0,
    "22_commits": 0,
    "15_committer_num": 0,
    "16_committer_num": 0,
    "17_committer_num": 1,
    "18_committer_num": 2,
    "19_committer_num": 0,
    "20_committer_num": 1,
    "21_committer_num": 0,
    "22_committer_num": 0
}{
    "stargazer_date": {
        "1052283": "2017-11-21T16:31:50",
        "5002584": "2017-12-15T03:42:41",
        "886074": "2018-03-05T01:52:12",
        "7166949": "2018-03-05T06:50:34",
        "18742612": "2018-03-05T13:11:45",
        "752519": "2018-03-09T08:43:14",
        "487251": "2018-03-13T15:32:03",
        "27948156": "2018-04-15T08:12:43",
        "7523401": "2018-05-01T08:49:26",
        "23136769": "2018-07-07T12:04:55",
        "36709681": "2018-10-04T11:24:44",
        "24801091": "2018-12-08T01:49:53",
        "3466459": "2019-02-27T19:07:50",
        "5259757": "2019-06-03T07:28:14",
        "4246081": "2019-06-04T14:33:46",
        "26103257": "2019-07-16T06:07:10",
        "1031885": "2020-07-20T12:49:49",
        "45456552": "2020-07-21T02:47:55",
        "20376933": "2020-09-14T09:52:47",
        "7006130": "2020-09-15T07:01:26",
        "35718148": "2020-09-28T08:18:33",
        "38804442": "2020-10-26T02:57:06",
        "19676712": "2020-12-27T18:02:15",
        "75029538": "2021-01-18T23:21:29",
        "11600411": "2021-02-07T19:04:55",
        "38674477": "2021-02-26T08:07:33",
        "31497506": "2021-03-18T11:58:40",
        "1536603": "2021-04-07T16:26:43",
        "24663664": "2021-06-01T06:54:41",
        "5036965": "2021-08-09T10:33:12",
        "60866570": "2021-09-29T12:27:49",
        "28684708": "2021-11-10T09:04:29",
        "10385396": "2021-11-21T11:46:31",
        "42175303": "2021-11-22T10:58:37",
        "29632248": "2021-12-28T03:16:21",
        "320582": "2022-03-23T18:36:59",
        "86563676": "2022-04-07T06:46:19",
        "9450866": "2022-06-25T19:37:25",
        "4922024": "2022-08-12T19:28:41",
        "7644267": "2022-09-01T14:58:07",
        "65118534": "2022-09-06T02:19:17",
        "10857288": "2022-09-07T08:42:10",
        "113411903": "2022-10-12T07:07:29"
    }
}[
    {
        "GHA": {}
    },
    {
        "Travis": []
    },
    {
        "CircleCI": []
    },
    {
        "AppVeyor": []
    },
    {
        "Azure": []
    },
    {
        "GitLab": []
    },
    {
        "Jenkins": []
    }
]