{
    "id": 55086122,
    "name": "react-native-push-notification",
    "full_name": "airbnb/react-native-push-notification",
    "org_name": "Airbnb",
    "org_id": 698437,
    "created_at": "2016-03-30T18:13:09",
    "pushed_at": "2023-03-04T01:04:00",
    "updated_at": "2022-02-11T17:46:38",
    "isFork": true,
    "forks": 14,
    "forks_count": 14,
    "has_downloads": true,
    "has_issues": false,
    "has_pages": false,
    "has_projects": true,
    "has_wiki": false,
    "homepage": "",
    "language": "Java",
    "open_issues": 0,
    "open_issues_count": 0,
    "size": 25,
    "stargazers_count": 63,
    "subscribers_count": 23,
    "watchers": 63,
    "watchers_count": 63,
    "first_commit": "2015-12-14T19:56:33",
    "last_commit": "2016-03-30T18:13:48",
    "branches_count": 1,
    "commit_comments_count": 0,
    "commits_count": 26,
    "countributors_count": 5,
    "downloads_count": 0,
    "events_count": 0,
    "issues_count": 0,
    "labels_count": 7,
    "milestones_count": 0,
    "PR_count": 0,
    "open_PR_count": 0,
    "readme_size": 6607,
    "release_count": 0,
    "topic_count": 0,
    "15_commits": 13,
    "16_commits": 13,
    "17_commits": 0,
    "18_commits": 0,
    "19_commits": 0,
    "20_commits": 0,
    "21_commits": 0,
    "22_commits": 0,
    "15_committer_num": 2,
    "16_committer_num": 4,
    "17_committer_num": 0,
    "18_committer_num": 0,
    "19_committer_num": 0,
    "20_committer_num": 0,
    "21_committer_num": 0,
    "22_committer_num": 0
}{
    "stargazer_date": {
        "1087221": "2016-03-31T06:12:01",
        "10987450": "2016-04-10T18:30:50",
        "1086630": "2016-04-15T14:24:27",
        "345851": "2016-05-07T10:55:03",
        "6451901": "2016-05-13T17:53:06",
        "5002532": "2016-06-04T05:14:48",
        "13491333": "2016-07-02T08:28:17",
        "106960": "2016-07-13T13:49:19",
        "1796906": "2016-08-25T16:32:38",
        "317584": "2016-09-05T17:24:29",
        "7957420": "2016-10-07T00:50:04",
        "1467820": "2016-10-17T15:35:47",
        "11869670": "2016-10-26T20:06:54",
        "4547862": "2016-10-27T06:04:11",
        "139904": "2016-10-27T21:19:46",
        "2515783": "2016-11-08T16:16:55",
        "765518": "2016-11-20T21:04:37",
        "954460": "2016-11-21T09:25:04",
        "3863380": "2016-11-23T03:55:19",
        "16708732": "2016-11-24T12:41:30",
        "1668289": "2016-12-04T00:12:42",
        "4936195": "2016-12-23T05:57:52",
        "42469": "2016-12-30T14:12:14",
        "3367703": "2017-01-08T02:19:40",
        "22449904": "2017-01-25T14:21:35",
        "5494638": "2017-02-01T06:24:22",
        "168509": "2017-02-02T18:44:40",
        "25133879": "2017-02-03T12:30:32",
        "15810634": "2017-02-21T14:08:19",
        "6381467": "2017-03-03T08:26:39",
        "5491536": "2017-03-13T19:16:19",
        "2100716": "2017-03-28T02:48:55",
        "1364487": "2017-03-31T18:53:13",
        "3314572": "2017-04-06T13:16:07",
        "956884": "2017-04-09T20:54:37",
        "20520880": "2017-04-20T13:38:44",
        "13679630": "2017-05-03T01:50:16",
        "6649459": "2017-05-12T08:04:36",
        "7471477": "2017-06-20T22:33:15",
        "4679231": "2017-07-15T22:45:55",
        "8342706": "2017-07-20T14:15:54",
        "406045": "2017-08-10T07:59:28",
        "1748351": "2017-10-05T16:36:52",
        "5455419": "2017-10-11T06:51:39",
        "7310257": "2017-10-12T04:37:59",
        "11521721": "2017-11-09T06:42:49",
        "2784590": "2017-12-05T09:23:46",
        "25086471": "2018-02-13T08:51:18",
        "1344309": "2018-03-01T16:16:02",
        "29376083": "2018-05-05T21:22:00",
        "11399538": "2018-05-15T16:32:49",
        "11306782": "2018-06-18T00:43:38",
        "3653520": "2018-08-01T10:44:16",
        "11714950": "2018-09-03T13:11:40",
        "13989549": "2018-09-04T14:43:19",
        "42984807": "2019-06-05T20:09:09",
        "55661881": "2019-10-30T09:33:55",
        "7087157": "2020-01-06T22:40:21",
        "12469814": "2020-01-21T14:26:42",
        "30437682": "2020-01-22T10:06:30",
        "11887909": "2020-03-26T06:14:27",
        "6874272": "2020-04-24T23:40:45",
        "55561087": "2022-02-11T17:46:38"
    }
}[
    {
        "GHA": {}
    },
    {
        "Travis": []
    },
    {
        "CircleCI": []
    },
    {
        "AppVeyor": []
    },
    {
        "Azure": []
    },
    {
        "GitLab": []
    },
    {
        "Jenkins": []
    }
]