{
    "id": 144957917,
    "name": "workspace-android-vcsdk",
    "full_name": "citrix/workspace-android-vcsdk",
    "org_name": "Citrix",
    "org_id": 1635391,
    "created_at": "2018-08-16T08:13:22",
    "pushed_at": "2021-04-22T20:03:07",
    "updated_at": "2021-04-22T20:03:06",
    "isFork": false,
    "forks": 0,
    "forks_count": 0,
    "has_downloads": true,
    "has_issues": true,
    "has_pages": true,
    "has_projects": true,
    "has_wiki": true,
    "homepage": null,
    "language": null,
    "open_issues": 0,
    "open_issues_count": 0,
    "size": 15763,
    "stargazers_count": 0,
    "subscribers_count": 7,
    "watchers": 0,
    "watchers_count": 0,
    "first_commit": "2017-02-08T15:09:39",
    "last_commit": "2021-04-22T20:03:03",
    "branches_count": 4,
    "commit_comments_count": 0,
    "commits_count": 30,
    "countributors_count": 3,
    "downloads_count": 0,
    "events_count": 0,
    "issues_count": 0,
    "labels_count": 8,
    "milestones_count": 0,
    "PR_count": 3,
    "open_PR_count": 0,
    "readme_size": 0,
    "release_count": 0,
    "topic_count": 0,
    "15_commits": 0,
    "16_commits": 0,
    "17_commits": 11,
    "18_commits": 11,
    "19_commits": 1,
    "20_commits": 4,
    "21_commits": 3,
    "22_commits": 0,
    "15_committer_num": 0,
    "16_committer_num": 0,
    "17_committer_num": 1,
    "18_committer_num": 2,
    "19_committer_num": 1,
    "20_committer_num": 1,
    "21_committer_num": 2,
    "22_committer_num": 0
}{
    "stargazer_date": {}
}[
    {
        "GHA": {}
    },
    {
        "Travis": []
    },
    {
        "CircleCI": []
    },
    {
        "AppVeyor": []
    },
    {
        "Azure": []
    },
    {
        "GitLab": []
    },
    {
        "Jenkins": []
    }
]