{
    "id": 153039618,
    "name": "PublishURLContent",
    "full_name": "citrix/PublishURLContent",
    "org_name": "Citrix",
    "org_id": 1635391,
    "created_at": "2018-10-15T02:04:44",
    "pushed_at": "2019-01-14T22:56:17",
    "updated_at": "2022-08-08T06:03:27",
    "isFork": false,
    "forks": 2,
    "forks_count": 2,
    "has_downloads": true,
    "has_issues": true,
    "has_pages": false,
    "has_projects": true,
    "has_wiki": true,
    "homepage": null,
    "language": "C#",
    "open_issues": 6,
    "open_issues_count": 6,
    "size": 400,
    "stargazers_count": 5,
    "subscribers_count": 5,
    "watchers": 5,
    "watchers_count": 5,
    "first_commit": "2018-10-14T22:52:44",
    "last_commit": "2019-01-04T04:12:27",
    "branches_count": 2,
    "commit_comments_count": 0,
    "commits_count": 7,
    "countributors_count": 1,
    "downloads_count": 0,
    "events_count": 0,
    "issues_count": 6,
    "labels_count": 9,
    "milestones_count": 0,
    "PR_count": 2,
    "open_PR_count": 0,
    "readme_size": 2278,
    "release_count": 2,
    "topic_count": 0,
    "15_commits": 0,
    "16_commits": 0,
    "17_commits": 0,
    "18_commits": 6,
    "19_commits": 1,
    "20_commits": 0,
    "21_commits": 0,
    "22_commits": 0,
    "15_committer_num": 0,
    "16_committer_num": 0,
    "17_committer_num": 0,
    "18_committer_num": 1,
    "19_committer_num": 1,
    "20_committer_num": 0,
    "21_committer_num": 0,
    "22_committer_num": 0
}{
    "stargazer_date": {
        "15822457": "2018-11-03T19:17:15",
        "14218733": "2019-01-04T14:41:27",
        "50457605": "2019-09-11T11:43:54",
        "17481561": "2020-10-19T08:32:39",
        "109990671": "2022-08-08T06:03:27"
    }
}[
    {
        "GHA": {}
    },
    {
        "Travis": []
    },
    {
        "CircleCI": []
    },
    {
        "AppVeyor": []
    },
    {
        "Azure": []
    },
    {
        "GitLab": []
    },
    {
        "Jenkins": []
    }
]