{
    "id": 75926982,
    "name": "qfetch-m3u8",
    "full_name": "qiniu/qfetch-m3u8",
    "org_name": "Qiniu Cloud",
    "org_id": 1563636,
    "created_at": "2016-12-08T10:17:18",
    "pushed_at": "2018-07-17T09:39:04",
    "updated_at": "2020-02-27T03:00:07",
    "isFork": false,
    "forks": 2,
    "forks_count": 2,
    "has_downloads": true,
    "has_issues": true,
    "has_pages": false,
    "has_projects": true,
    "has_wiki": true,
    "homepage": null,
    "language": "Go",
    "open_issues": 0,
    "open_issues_count": 0,
    "size": 43,
    "stargazers_count": 5,
    "subscribers_count": 3,
    "watchers": 5,
    "watchers_count": 5,
    "first_commit": "2015-06-02T09:38:07",
    "last_commit": "2018-07-17T09:38:59",
    "branches_count": 2,
    "commit_comments_count": 0,
    "commits_count": 48,
    "countributors_count": 1,
    "downloads_count": 0,
    "events_count": 0,
    "issues_count": 0,
    "labels_count": 7,
    "milestones_count": 0,
    "PR_count": 0,
    "open_PR_count": 0,
    "readme_size": 7848,
    "release_count": 0,
    "topic_count": 0,
    "15_commits": 14,
    "16_commits": 24,
    "17_commits": 3,
    "18_commits": 7,
    "19_commits": 0,
    "20_commits": 0,
    "21_commits": 0,
    "22_commits": 0,
    "15_committer_num": 1,
    "16_committer_num": 1,
    "17_committer_num": 1,
    "18_committer_num": 1,
    "19_committer_num": 0,
    "20_committer_num": 0,
    "21_committer_num": 0,
    "22_committer_num": 0
}{
    "stargazer_date": {
        "5317219": "2017-04-13T08:13:58",
        "2363295": "2017-05-15T11:18:59",
        "483757": "2018-02-08T11:20:08",
        "6963565": "2018-10-16T16:58:27",
        "7412609": "2020-02-15T15:31:30"
    }
}[
    {
        "GHA": {}
    },
    {
        "Travis": []
    },
    {
        "CircleCI": []
    },
    {
        "AppVeyor": []
    },
    {
        "Azure": []
    },
    {
        "GitLab": []
    },
    {
        "Jenkins": []
    }
]