{
    "id": 239556677,
    "name": "bazel-ls-eclipse",
    "full_name": "salesforce/bazel-ls-eclipse",
    "org_name": "Salesforce",
    "org_id": 453694,
    "created_at": "2020-02-10T16:21:29",
    "pushed_at": "2022-02-12T14:36:36",
    "updated_at": "2023-01-28T03:08:27",
    "isFork": false,
    "forks": 4,
    "forks_count": 4,
    "has_downloads": true,
    "has_issues": true,
    "has_pages": false,
    "has_projects": true,
    "has_wiki": true,
    "homepage": "",
    "language": "Java",
    "open_issues": 20,
    "open_issues_count": 20,
    "size": 23230,
    "stargazers_count": 8,
    "subscribers_count": 11,
    "watchers": 8,
    "watchers_count": 8,
    "first_commit": "2020-04-10T12:10:53",
    "last_commit": "2022-02-12T14:36:36",
    "branches_count": 21,
    "commit_comments_count": 9,
    "commits_count": 175,
    "countributors_count": 9,
    "downloads_count": 0,
    "events_count": 0,
    "issues_count": 20,
    "labels_count": 11,
    "milestones_count": 3,
    "PR_count": 55,
    "open_PR_count": 0,
    "readme_size": 3073,
    "release_count": 0,
    "topic_count": 0,
    "15_commits": 0,
    "16_commits": 0,
    "17_commits": 0,
    "18_commits": 0,
    "19_commits": 0,
    "20_commits": 106,
    "21_commits": 68,
    "22_commits": 1,
    "15_committer_num": 0,
    "16_committer_num": 0,
    "17_committer_num": 0,
    "18_committer_num": 0,
    "19_committer_num": 0,
    "20_committer_num": 6,
    "21_committer_num": 6,
    "22_committer_num": 1
}{
    "stargazer_date": {
        "695890": "2020-04-02T14:23:22",
        "6152690": "2020-04-02T14:25:15",
        "513595": "2020-04-15T15:12:00",
        "719828": "2020-05-09T14:51:48",
        "5058358": "2020-10-04T22:23:33",
        "921358": "2021-04-28T17:52:58",
        "1150337": "2021-06-19T07:11:20"
    }
}[
    {
        "GHA": [
            {
                "file_name": ".github/workflows/build.yml",
                "commit_date": "2021-02-11T07:46:10",
                "status": "modified",
                "first_commit": "2020-02-19T09:43:23",
                "last_commit": "2021-02-11T07:46:10",
                "CI_type": "GHA",
                "sha": "c0d5f4cb4b394e70aca5a373ebcffa16e15b2334"
            },
            {
                "file_name": ".github/workflows/build.yml",
                "commit_date": "2020-04-01T15:52:35",
                "status": "modified",
                "first_commit": "2020-02-19T09:43:23",
                "last_commit": "2021-02-11T07:46:10",
                "CI_type": "GHA",
                "sha": "3f2731933646cf077ffc5ebd2db23fa50de2c60f"
            },
            {
                "file_name": ".github/workflows/build.yml",
                "commit_date": "2020-03-25T07:49:08",
                "status": "modified",
                "first_commit": "2020-02-19T09:43:23",
                "last_commit": "2021-02-11T07:46:10",
                "CI_type": "GHA",
                "sha": "02a4bbfe086f2cb6d683f30ba5f7258bfb2c7e1b"
            },
            {
                "file_name": ".github/workflows/build.yml",
                "commit_date": "2020-03-24T19:56:58",
                "status": "modified",
                "first_commit": "2020-02-19T09:43:23",
                "last_commit": "2021-02-11T07:46:10",
                "CI_type": "GHA",
                "sha": "be1a613294c738533cfdee4bbc52e260c3943f0a"
            },
            {
                "file_name": ".github/workflows/build.yml",
                "commit_date": "2020-03-20T17:56:11",
                "status": "modified",
                "first_commit": "2020-02-19T09:43:23",
                "last_commit": "2021-02-11T07:46:10",
                "CI_type": "GHA",
                "sha": "552dfb1096dad835e3f3d69e238fd7ef63536a9b"
            },
            {
                "file_name": ".github/workflows/build.yml",
                "commit_date": "2020-03-19T07:52:30",
                "status": "modified",
                "first_commit": "2020-02-19T09:43:23",
                "last_commit": "2021-02-11T07:46:10",
                "CI_type": "GHA",
                "sha": "5a7cead5e471e0f5ab74872c820dfca43b110676"
            },
            {
                "file_name": ".github/workflows/build.yml",
                "commit_date": "2020-03-10T11:35:33",
                "status": "modified",
                "first_commit": "2020-02-19T09:43:23",
                "last_commit": "2021-02-11T07:46:10",
                "CI_type": "GHA",
                "sha": "9074f323bc78bb406985c1d3a41cb5984a97f82c"
            },
            {
                "file_name": ".github/workflows/build.yml",
                "commit_date": "2020-03-10T11:33:56",
                "status": "modified",
                "first_commit": "2020-02-19T09:43:23",
                "last_commit": "2021-02-11T07:46:10",
                "CI_type": "GHA",
                "sha": "0d6a0fcdedb770468e7613a0418fe9879be43c33"
            },
            {
                "file_name": ".github/workflows/build.yml",
                "commit_date": "2020-03-10T09:42:56",
                "status": "modified",
                "first_commit": "2020-02-19T09:43:23",
                "last_commit": "2021-02-11T07:46:10",
                "CI_type": "GHA",
                "sha": "13786a73329ef7a4aa3c97c45c699e9f86c44fc7"
            },
            {
                "file_name": ".github/workflows/build.yml",
                "commit_date": "2020-03-10T09:28:29",
                "status": "modified",
                "first_commit": "2020-02-19T09:43:23",
                "last_commit": "2021-02-11T07:46:10",
                "CI_type": "GHA",
                "sha": "96cd6fd9095b1c46098f40df4e92c40aec229b0b"
            },
            {
                "file_name": ".github/workflows/build.yml",
                "commit_date": "2020-03-05T10:44:11",
                "status": "modified",
                "first_commit": "2020-02-19T09:43:23",
                "last_commit": "2021-02-11T07:46:10",
                "CI_type": "GHA",
                "sha": "43c63e43a0e469f20b3ee22abcc04a3efada877d"
            },
            {
                "file_name": ".github/workflows/build.yml",
                "commit_date": "2020-02-27T10:39:47",
                "status": "modified",
                "first_commit": "2020-02-19T09:43:23",
                "last_commit": "2021-02-11T07:46:10",
                "CI_type": "GHA",
                "sha": "3caa739f5daf6665e85fb04e2f69c13181837e00"
            },
            {
                "file_name": ".github/workflows/build.yml",
                "commit_date": "2020-02-24T15:05:57",
                "status": "modified",
                "first_commit": "2020-02-19T09:43:23",
                "last_commit": "2021-02-11T07:46:10",
                "CI_type": "GHA",
                "sha": "23366e29ba5974218a4107c3da5887e8aa7e22ea"
            },
            {
                "file_name": ".github/workflows/build.yml",
                "commit_date": "2020-02-19T09:43:23",
                "status": "added",
                "first_commit": "2020-02-19T09:43:23",
                "last_commit": "2021-02-11T07:46:10",
                "CI_type": "GHA",
                "sha": "33633f52065be0346a106cc09717f9b1ac12d594"
            }
        ]
    },
    {
        "Travis": []
    },
    {
        "CircleCI": []
    },
    {
        "AppVeyor": []
    },
    {
        "Azure": []
    },
    {
        "GitLab": []
    },
    {
        "Jenkins": []
    }
]