{
    "id": 144076419,
    "name": "node-dependency-analysis",
    "full_name": "google/node-dependency-analysis",
    "org_name": "Google",
    "org_id": 1342004,
    "created_at": "2018-08-08T23:05:17",
    "pushed_at": "2018-12-05T22:42:49",
    "updated_at": "2023-01-28T06:00:54",
    "isFork": false,
    "forks": 8,
    "forks_count": 8,
    "has_downloads": true,
    "has_issues": true,
    "has_pages": false,
    "has_projects": true,
    "has_wiki": true,
    "homepage": null,
    "language": "TypeScript",
    "open_issues": 0,
    "open_issues_count": 0,
    "size": 197,
    "stargazers_count": 14,
    "subscribers_count": 8,
    "watchers": 14,
    "watchers_count": 14,
    "first_commit": "2018-07-17T22:01:54",
    "last_commit": "2018-09-08T00:00:32",
    "branches_count": 6,
    "commit_comments_count": 0,
    "commits_count": 43,
    "countributors_count": 3,
    "downloads_count": 0,
    "events_count": 1,
    "issues_count": 0,
    "labels_count": 8,
    "milestones_count": 0,
    "PR_count": 31,
    "open_PR_count": 0,
    "readme_size": 4800,
    "release_count": 0,
    "topic_count": 0,
    "15_commits": 0,
    "16_commits": 0,
    "17_commits": 0,
    "18_commits": 43,
    "19_commits": 0,
    "20_commits": 0,
    "21_commits": 0,
    "22_commits": 0,
    "15_committer_num": 0,
    "16_committer_num": 0,
    "17_committer_num": 0,
    "18_committer_num": 3,
    "19_committer_num": 0,
    "20_committer_num": 0,
    "21_committer_num": 0,
    "22_committer_num": 0
}{
    "stargazer_date": {
        "20604732": "2018-08-08T23:58:15",
        "19519564": "2018-09-17T00:25:12",
        "2929140": "2018-11-13T10:52:56",
        "14249985": "2018-11-15T21:59:27",
        "5408269": "2018-11-27T13:29:51",
        "11882787": "2019-04-22T05:40:24",
        "770675": "2019-05-29T12:24:43",
        "35314276": "2019-12-16T22:00:38",
        "118918": "2020-02-13T13:36:36",
        "9933677": "2020-03-14T10:09:14",
        "10324554": "2020-12-08T15:23:49",
        "47697490": "2020-12-08T15:51:38",
        "11549103": "2021-08-12T07:23:07",
        "79616833": "2021-10-12T15:24:38"
    }
}[
    {
        "GHA": {}
    },
    {
        "Travis": []
    },
    {
        "CircleCI": [
            {
                "file_name": "/.circleci/config.yml",
                "commit_date": "2018-08-18T00:19:50",
                "status": "added",
                "first_commit": "2018-08-18T00:19:50",
                "last_commit": "2018-08-18T00:19:50",
                "CI_type": "CircleCI",
                "sha": "93054c8c72a58b034f2fb8756aa9256b87c18d91"
            }
        ]
    },
    {
        "AppVeyor": []
    },
    {
        "Azure": []
    },
    {
        "GitLab": []
    },
    {
        "Jenkins": []
    }
]