{
    "id": 167341886,
    "name": "emoji-segmenter",
    "full_name": "google/emoji-segmenter",
    "org_name": "Google",
    "org_id": 1342004,
    "created_at": "2019-01-24T09:37:36",
    "pushed_at": "2021-10-12T09:47:33",
    "updated_at": "2023-02-16T12:56:52",
    "isFork": false,
    "forks": 10,
    "forks_count": 10,
    "has_downloads": true,
    "has_issues": true,
    "has_pages": false,
    "has_projects": true,
    "has_wiki": true,
    "homepage": "",
    "language": "C",
    "open_issues": 2,
    "open_issues_count": 2,
    "size": 9,
    "stargazers_count": 49,
    "subscribers_count": 11,
    "watchers": 49,
    "watchers_count": 49,
    "first_commit": "2019-01-24T10:55:31",
    "last_commit": "2019-01-29T12:36:22",
    "branches_count": 1,
    "commit_comments_count": 0,
    "commits_count": 2,
    "countributors_count": 1,
    "downloads_count": 0,
    "events_count": 2,
    "issues_count": 2,
    "labels_count": 8,
    "milestones_count": 0,
    "PR_count": 1,
    "open_PR_count": 1,
    "readme_size": 3459,
    "release_count": 0,
    "topic_count": 4,
    "15_commits": 0,
    "16_commits": 0,
    "17_commits": 0,
    "18_commits": 0,
    "19_commits": 2,
    "20_commits": 0,
    "21_commits": 0,
    "22_commits": 0,
    "15_committer_num": 0,
    "16_committer_num": 0,
    "17_committer_num": 0,
    "18_committer_num": 0,
    "19_committer_num": 1,
    "20_committer_num": 0,
    "21_committer_num": 0,
    "22_committer_num": 0
}{
    "stargazer_date": {
        "8467641": "2019-01-30T01:31:20",
        "142891": "2019-02-01T00:58:31",
        "1021784": "2019-02-06T09:06:38",
        "18673814": "2019-02-21T05:08:56",
        "2268761": "2019-03-03T18:18:05",
        "606772": "2019-04-10T18:37:52",
        "25974855": "2019-05-08T20:11:15",
        "9510143": "2019-05-25T16:23:59",
        "1660253": "2019-06-17T09:48:07",
        "78187": "2019-09-29T21:33:55",
        "19375079": "2019-12-12T15:19:59",
        "3063662": "2019-12-24T17:37:13",
        "49222178": "2020-03-05T08:57:40",
        "9933677": "2020-03-14T09:02:05",
        "27680519": "2020-04-13T16:43:24",
        "56763": "2020-04-17T16:56:59",
        "47627985": "2020-05-12T13:57:05",
        "3108136": "2020-08-18T12:30:42",
        "81942": "2020-09-28T12:12:44",
        "26198264": "2020-09-28T14:44:29",
        "35000542": "2020-09-28T15:07:15",
        "5939997": "2020-09-28T17:04:24",
        "10156994": "2020-09-28T19:18:48",
        "3759759": "2020-09-29T02:03:03",
        "919300": "2020-09-29T04:27:59",
        "32855384": "2020-10-01T11:41:24",
        "64213355": "2020-10-08T13:21:50",
        "63785599": "2020-10-24T16:44:40",
        "68488378": "2021-04-14T06:24:11",
        "36937771": "2021-04-20T20:38:17",
        "5275194": "2021-05-09T18:01:56",
        "6939968": "2021-06-04T16:43:59",
        "3500109": "2021-09-02T14:50:29",
        "2009799": "2021-09-18T15:05:09",
        "68473617": "2021-10-04T19:49:29",
        "8097890": "2021-10-12T14:38:44",
        "30958533": "2021-10-12T17:31:50",
        "56444651": "2021-10-12T18:09:06",
        "13083772": "2021-10-13T11:27:35",
        "26296949": "2021-10-15T01:03:18",
        "50616749": "2021-10-16T12:14:39",
        "54918378": "2022-01-11T06:48:41",
        "44344403": "2022-03-31T15:00:52",
        "82948085": "2022-07-14T20:31:17",
        "167209": "2022-09-17T11:40:31",
        "1481527": "2022-12-08T02:59:15",
        "10107543": "2023-01-22T03:39:32",
        "112587492": "2023-02-11T10:38:31",
        "20896709": "2023-02-16T12:56:52"
    }
}[
    {
        "GHA": {}
    },
    {
        "Travis": []
    },
    {
        "CircleCI": []
    },
    {
        "AppVeyor": []
    },
    {
        "Azure": []
    },
    {
        "GitLab": []
    },
    {
        "Jenkins": []
    }
]