{
    "id": 121109429,
    "name": "gh-ost-ci-env",
    "full_name": "github/gh-ost-ci-env",
    "org_name": "GitHub",
    "org_id": 9919,
    "created_at": "2018-02-11T09:54:29",
    "pushed_at": "2022-11-25T18:56:30",
    "updated_at": "2023-03-05T12:59:45",
    "isFork": false,
    "forks": 13,
    "forks_count": 13,
    "has_downloads": true,
    "has_issues": true,
    "has_pages": false,
    "has_projects": true,
    "has_wiki": true,
    "homepage": null,
    "language": "Shell",
    "open_issues": 0,
    "open_issues_count": 0,
    "size": 455106,
    "stargazers_count": 10,
    "subscribers_count": 236,
    "watchers": 10,
    "watchers_count": 10,
    "first_commit": "2018-02-11T09:54:31",
    "last_commit": "2022-11-25T18:56:30",
    "branches_count": 1,
    "commit_comments_count": 0,
    "commits_count": 32,
    "countributors_count": 4,
    "downloads_count": 0,
    "events_count": 2,
    "issues_count": 0,
    "labels_count": 9,
    "milestones_count": 0,
    "PR_count": 14,
    "open_PR_count": 0,
    "readme_size": 1142,
    "release_count": 0,
    "topic_count": 0,
    "15_commits": 0,
    "16_commits": 0,
    "17_commits": 0,
    "18_commits": 15,
    "19_commits": 0,
    "20_commits": 7,
    "21_commits": 3,
    "22_commits": 7,
    "15_committer_num": 0,
    "16_committer_num": 0,
    "17_committer_num": 0,
    "18_committer_num": 0,
    "19_committer_num": 0,
    "20_committer_num": 0,
    "21_committer_num": 2,
    "22_committer_num": 3
}{
    "stargazer_date": {
        "893920": "2018-02-11T12:51:16",
        "347371": "2018-02-11T17:07:57",
        "1129476": "2018-11-06T02:22:47",
        "8676743": "2019-06-26T07:08:03",
        "9933677": "2020-07-31T03:02:17",
        "11528358": "2021-01-21T11:34:34",
        "3202797": "2021-05-04T12:19:37",
        "33383463": "2021-07-19T03:10:53",
        "74206431": "2021-08-10T18:48:55",
        "89616705": "2023-01-25T09:02:56"
    }
}[
    {
        "GHA": {}
    },
    {
        "Travis": []
    },
    {
        "CircleCI": []
    },
    {
        "AppVeyor": []
    },
    {
        "Azure": []
    },
    {
        "GitLab": []
    },
    {
        "Jenkins": []
    }
]