{
    "id": 355612793,
    "name": "shim-review",
    "full_name": "oracle/shim-review",
    "org_name": "Oracle",
    "org_id": 4430336,
    "created_at": "2021-04-07T16:28:58",
    "pushed_at": "2022-12-08T02:40:50",
    "updated_at": "2022-05-30T20:38:19",
    "isFork": true,
    "forks": 4,
    "forks_count": 4,
    "has_downloads": true,
    "has_issues": false,
    "has_pages": false,
    "has_projects": true,
    "has_wiki": true,
    "homepage": null,
    "language": null,
    "open_issues": 0,
    "open_issues_count": 0,
    "size": 10373,
    "stargazers_count": 1,
    "subscribers_count": 2,
    "watchers": 1,
    "watchers_count": 1,
    "first_commit": "2017-04-13T15:09:51",
    "last_commit": "2022-04-21T19:37:15",
    "branches_count": 8,
    "commit_comments_count": 0,
    "commits_count": 30,
    "countributors_count": 11,
    "downloads_count": 0,
    "events_count": 0,
    "issues_count": 0,
    "labels_count": 9,
    "milestones_count": 0,
    "PR_count": 0,
    "open_PR_count": 0,
    "readme_size": 11217,
    "release_count": 0,
    "topic_count": 0,
    "15_commits": 0,
    "16_commits": 0,
    "17_commits": 4,
    "18_commits": 3,
    "19_commits": 0,
    "20_commits": 4,
    "21_commits": 12,
    "22_commits": 7,
    "15_committer_num": 0,
    "16_committer_num": 0,
    "17_committer_num": 2,
    "18_committer_num": 1,
    "19_committer_num": 0,
    "20_committer_num": 1,
    "21_committer_num": 7,
    "22_committer_num": 2
}{
    "stargazer_date": {
        "9279159": "2022-05-29T22:40:05"
    }
}[
    {
        "GHA": {}
    },
    {
        "Travis": []
    },
    {
        "CircleCI": []
    },
    {
        "AppVeyor": []
    },
    {
        "Azure": []
    },
    {
        "GitLab": []
    },
    {
        "Jenkins": []
    }
]