{
    "id": 72055454,
    "name": "paradox-testng",
    "full_name": "oracle/paradox-testng",
    "org_name": "Oracle",
    "org_id": 4430336,
    "created_at": "2016-10-27T00:13:14",
    "pushed_at": "2022-01-07T18:02:37",
    "updated_at": "2022-01-06T22:01:43",
    "isFork": false,
    "forks": 13,
    "forks_count": 13,
    "has_downloads": true,
    "has_issues": true,
    "has_pages": false,
    "has_projects": true,
    "has_wiki": true,
    "homepage": null,
    "language": "Groovy",
    "open_issues": 1,
    "open_issues_count": 1,
    "size": 140,
    "stargazers_count": 2,
    "subscribers_count": 6,
    "watchers": 2,
    "watchers_count": 2,
    "first_commit": "2016-10-27T00:10:33",
    "last_commit": "2022-01-06T22:01:40",
    "branches_count": 1,
    "commit_comments_count": 0,
    "commits_count": 31,
    "countributors_count": 3,
    "downloads_count": 0,
    "events_count": 0,
    "issues_count": 1,
    "labels_count": 7,
    "milestones_count": 0,
    "PR_count": 9,
    "open_PR_count": 1,
    "readme_size": 1627,
    "release_count": 0,
    "topic_count": 1,
    "15_commits": 0,
    "16_commits": 2,
    "17_commits": 19,
    "18_commits": 0,
    "19_commits": 9,
    "20_commits": 0,
    "21_commits": 0,
    "22_commits": 1,
    "15_committer_num": 0,
    "16_committer_num": 0,
    "17_committer_num": 3,
    "18_committer_num": 0,
    "19_committer_num": 1,
    "20_committer_num": 0,
    "21_committer_num": 0,
    "22_committer_num": 1
}{
    "stargazer_date": {
        "39334191": "2019-03-06T18:32:18",
        "9933677": "2020-09-18T08:54:52"
    }
}[
    {
        "GHA": {}
    },
    {
        "Travis": [
            {
                "file_name": "/.travis.yml",
                "commit_date": "2017-05-09T16:58:17",
                "status": "modified",
                "first_commit": "2017-04-27T20:35:35",
                "last_commit": "2017-05-09T16:58:17",
                "CI_type": "Travis",
                "sha": "50b3993ed2159d7d975be415346095b194a9d7fb"
            },
            {
                "file_name": "/.travis.yml",
                "commit_date": "2017-05-09T16:50:13",
                "status": "modified",
                "first_commit": "2017-04-27T20:35:35",
                "last_commit": "2017-05-09T16:58:17",
                "CI_type": "Travis",
                "sha": "89800a7ba01d0642daed54db9bf8814770adbf32"
            },
            {
                "file_name": "/.travis.yml",
                "commit_date": "2017-05-09T16:36:01",
                "status": "modified",
                "first_commit": "2017-04-27T20:35:35",
                "last_commit": "2017-05-09T16:58:17",
                "CI_type": "Travis",
                "sha": "0ebedd31da999928176a9fd2e71a9cd9fc98b014"
            },
            {
                "file_name": "/.travis.yml",
                "commit_date": "2017-05-09T16:17:48",
                "status": "modified",
                "first_commit": "2017-04-27T20:35:35",
                "last_commit": "2017-05-09T16:58:17",
                "CI_type": "Travis",
                "sha": "351e3688a12bdd2903c563042bfe1235266db180"
            },
            {
                "file_name": "/.travis.yml",
                "commit_date": "2017-05-08T23:20:38",
                "status": "modified",
                "first_commit": "2017-04-27T20:35:35",
                "last_commit": "2017-05-09T16:58:17",
                "CI_type": "Travis",
                "sha": "0fe110ffe8f37de8108fa741c650386d62b7fa0c"
            },
            {
                "file_name": "/.travis.yml",
                "commit_date": "2017-04-27T20:35:35",
                "status": "added",
                "first_commit": "2017-04-27T20:35:35",
                "last_commit": "2017-05-09T16:58:17",
                "CI_type": "Travis",
                "sha": "df152f35e3953969896d5d0cf7b6ec3fa5c44932"
            }
        ]
    },
    {
        "CircleCI": []
    },
    {
        "AppVeyor": []
    },
    {
        "Azure": []
    },
    {
        "GitLab": []
    },
    {
        "Jenkins": []
    }
]