{
    "id": 58933486,
    "name": "northshore",
    "full_name": "Mirantis/northshore",
    "org_name": "Mirantis Inc.",
    "org_id": 609319,
    "created_at": "2016-05-16T13:14:08",
    "pushed_at": "2020-02-26T12:00:12",
    "updated_at": "2019-08-29T15:00:57",
    "isFork": false,
    "forks": 6,
    "forks_count": 6,
    "has_downloads": true,
    "has_issues": true,
    "has_pages": false,
    "has_projects": true,
    "has_wiki": true,
    "homepage": null,
    "language": "Go",
    "open_issues": 1,
    "open_issues_count": 1,
    "size": 38728,
    "stargazers_count": 1,
    "subscribers_count": 5,
    "watchers": 1,
    "watchers_count": 1,
    "first_commit": "2016-07-14T16:50:13",
    "last_commit": "2016-09-03T14:40:09",
    "branches_count": 2,
    "commit_comments_count": 0,
    "commits_count": 295,
    "countributors_count": 3,
    "downloads_count": 0,
    "events_count": 0,
    "issues_count": 1,
    "labels_count": 9,
    "milestones_count": 0,
    "PR_count": 73,
    "open_PR_count": 1,
    "readme_size": 1258,
    "release_count": 0,
    "topic_count": 0,
    "15_commits": 0,
    "16_commits": 295,
    "17_commits": 0,
    "18_commits": 0,
    "19_commits": 0,
    "20_commits": 0,
    "21_commits": 0,
    "22_commits": 0,
    "15_committer_num": 0,
    "16_committer_num": 3,
    "17_committer_num": 0,
    "18_committer_num": 0,
    "19_committer_num": 0,
    "20_committer_num": 0,
    "21_committer_num": 0,
    "22_committer_num": 0
}{
    "stargazer_date": {
        "51771": "2016-08-26T23:29:01"
    }
}[
    {
        "GHA": {}
    },
    {
        "Travis": [
            {
                "file_name": "/.travis.yml",
                "commit_date": "2016-06-30T08:23:49",
                "status": "modified",
                "first_commit": "2016-06-02T20:28:42",
                "last_commit": "2016-06-30T08:23:49",
                "CI_type": "Travis",
                "sha": "6bd45d264970d54b40f2fce684d302cf234c0805"
            },
            {
                "file_name": "/.travis.yml",
                "commit_date": "2016-06-30T07:28:28",
                "status": "modified",
                "first_commit": "2016-06-02T20:28:42",
                "last_commit": "2016-06-30T08:23:49",
                "CI_type": "Travis",
                "sha": "26f413337183c751448d0e99b79d52bcfe863c31"
            },
            {
                "file_name": "/.travis.yml",
                "commit_date": "2016-06-29T12:24:17",
                "status": "modified",
                "first_commit": "2016-06-02T20:28:42",
                "last_commit": "2016-06-30T08:23:49",
                "CI_type": "Travis",
                "sha": "51b8b2cc61017a601b160c93fcd3e95cb466d41c"
            },
            {
                "file_name": "/.travis.yml",
                "commit_date": "2016-06-16T10:36:17",
                "status": "modified",
                "first_commit": "2016-06-02T20:28:42",
                "last_commit": "2016-06-30T08:23:49",
                "CI_type": "Travis",
                "sha": "c8fe6b879f46ea37fab7be32620cabc069099bfb"
            },
            {
                "file_name": "/.travis.yml",
                "commit_date": "2016-06-09T12:34:30",
                "status": "modified",
                "first_commit": "2016-06-02T20:28:42",
                "last_commit": "2016-06-30T08:23:49",
                "CI_type": "Travis",
                "sha": "b41935055df2e340af574c8517935369b0fc9400"
            },
            {
                "file_name": "/.travis.yml",
                "commit_date": "2016-06-02T20:28:42",
                "status": "added",
                "first_commit": "2016-06-02T20:28:42",
                "last_commit": "2016-06-30T08:23:49",
                "CI_type": "Travis",
                "sha": "cf599b79f83f95e9476805d803a9b6250bb5ac9b"
            }
        ]
    },
    {
        "CircleCI": []
    },
    {
        "AppVeyor": []
    },
    {
        "Azure": []
    },
    {
        "GitLab": []
    },
    {
        "Jenkins": []
    }
]