{
    "id": 24496188,
    "name": "redis-store",
    "full_name": "lingochamp/redis-store",
    "org_name": "LAIX Inc. (formerly LingoChamp Inc.)",
    "org_id": 7429349,
    "created_at": "2014-09-26T10:51:21",
    "pushed_at": "2013-11-05T09:54:54",
    "updated_at": "2016-01-01T16:17:20",
    "isFork": true,
    "forks": 0,
    "forks_count": 0,
    "has_downloads": true,
    "has_issues": false,
    "has_pages": false,
    "has_projects": true,
    "has_wiki": true,
    "homepage": "http://redis-store.org/redis-store",
    "language": null,
    "open_issues": 0,
    "open_issues_count": 0,
    "size": 4035,
    "stargazers_count": 1,
    "subscribers_count": 9,
    "watchers": 1,
    "watchers_count": 1,
    "first_commit": "2012-02-02T16:20:50",
    "last_commit": "2013-11-05T09:54:53",
    "branches_count": 6,
    "commit_comments_count": 0,
    "commits_count": 494,
    "countributors_count": 34,
    "downloads_count": 0,
    "events_count": 0,
    "issues_count": 0,
    "labels_count": 7,
    "milestones_count": 0,
    "PR_count": 0,
    "open_PR_count": 0,
    "readme_size": 1503,
    "release_count": 0,
    "topic_count": 0,
    "15_commits": 0,
    "16_commits": 0,
    "17_commits": 0,
    "18_commits": 0,
    "19_commits": 0,
    "20_commits": 0,
    "21_commits": 0,
    "22_commits": 0,
    "15_committer_num": 0,
    "16_committer_num": 0,
    "17_committer_num": 0,
    "18_committer_num": 0,
    "19_committer_num": 0,
    "20_committer_num": 0,
    "21_committer_num": 0,
    "22_committer_num": 0
}{
    "stargazer_date": {
        "8100661": "2016-01-01T16:17:20"
    }
}[
    {
        "GHA": {}
    },
    {
        "Travis": [
            {
                "file_name": "/.travis.yml",
                "commit_date": "2013-08-23T13:46:28",
                "status": "modified",
                "first_commit": "2011-08-23T18:17:07",
                "last_commit": "2013-08-23T13:46:28",
                "CI_type": "Travis",
                "sha": "e6f15c5e2ecfa1187c852edcc883a195c2b3d136"
            },
            {
                "file_name": "/.travis.yml",
                "commit_date": "2013-08-20T03:53:58",
                "status": "modified",
                "first_commit": "2011-08-23T18:17:07",
                "last_commit": "2013-08-23T13:46:28",
                "CI_type": "Travis",
                "sha": "440dd0fcef4aee35a19fd5d47d8f341e696e2151"
            },
            {
                "file_name": "/.travis.yml",
                "commit_date": "2013-07-23T12:15:57",
                "status": "modified",
                "first_commit": "2011-08-23T18:17:07",
                "last_commit": "2013-08-23T13:46:28",
                "CI_type": "Travis",
                "sha": "a9f0399d0506f5ac6d09d7a7ab488a4170c068bf"
            },
            {
                "file_name": "/.travis.yml",
                "commit_date": "2013-07-21T22:42:25",
                "status": "modified",
                "first_commit": "2011-08-23T18:17:07",
                "last_commit": "2013-08-23T13:46:28",
                "CI_type": "Travis",
                "sha": "7ef084ab9b53f90a819aaf125d54d77b29571cd9"
            },
            {
                "file_name": "/.travis.yml",
                "commit_date": "2013-06-27T02:12:53",
                "status": "modified",
                "first_commit": "2011-08-23T18:17:07",
                "last_commit": "2013-08-23T13:46:28",
                "CI_type": "Travis",
                "sha": "3cc7b3dc852f720b2390a598b2d088bdd6f206e5"
            },
            {
                "file_name": "/.travis.yml",
                "commit_date": "2013-05-02T22:38:38",
                "status": "modified",
                "first_commit": "2011-08-23T18:17:07",
                "last_commit": "2013-08-23T13:46:28",
                "CI_type": "Travis",
                "sha": "507935e85d200831d52a1afcaababbf4e7b9c507"
            },
            {
                "file_name": "/.travis.yml",
                "commit_date": "2012-11-24T16:38:58",
                "status": "modified",
                "first_commit": "2011-08-23T18:17:07",
                "last_commit": "2013-08-23T13:46:28",
                "CI_type": "Travis",
                "sha": "d5cfa27374e87933fce9f8b846af0e18ca27e5f3"
            },
            {
                "file_name": "/.travis.yml",
                "commit_date": "2012-06-26T08:42:47",
                "status": "modified",
                "first_commit": "2011-08-23T18:17:07",
                "last_commit": "2013-08-23T13:46:28",
                "CI_type": "Travis",
                "sha": "0225478b6030e0e82e1f7d82a05e11ffe6257db3"
            },
            {
                "file_name": "/.travis.yml",
                "commit_date": "2011-12-29T16:24:18",
                "status": "modified",
                "first_commit": "2011-08-23T18:17:07",
                "last_commit": "2013-08-23T13:46:28",
                "CI_type": "Travis",
                "sha": "9416933421570a73f6a7e30d90c66ade664c939c"
            },
            {
                "file_name": "/.travis.yml",
                "commit_date": "2011-12-25T12:02:04",
                "status": "modified",
                "first_commit": "2011-08-23T18:17:07",
                "last_commit": "2013-08-23T13:46:28",
                "CI_type": "Travis",
                "sha": "535a28b8e7fc875fea47780def3527e474a2e123"
            },
            {
                "file_name": "/.travis.yml",
                "commit_date": "2011-11-17T14:06:52",
                "status": "modified",
                "first_commit": "2011-08-23T18:17:07",
                "last_commit": "2013-08-23T13:46:28",
                "CI_type": "Travis",
                "sha": "200c1cd3234d8d2447c370664565d021ee407f2d"
            },
            {
                "file_name": "/.travis.yml",
                "commit_date": "2011-09-06T12:02:25",
                "status": "modified",
                "first_commit": "2011-08-23T18:17:07",
                "last_commit": "2013-08-23T13:46:28",
                "CI_type": "Travis",
                "sha": "29e81ba4813a1e0875dd1a07cffafa25b192e304"
            },
            {
                "file_name": "/.travis.yml",
                "commit_date": "2011-09-06T10:25:34",
                "status": "modified",
                "first_commit": "2011-08-23T18:17:07",
                "last_commit": "2013-08-23T13:46:28",
                "CI_type": "Travis",
                "sha": "5b64b8c683c33a4889a820fe897fa7110dc795cb"
            },
            {
                "file_name": "/.travis.yml",
                "commit_date": "2011-08-23T18:37:52",
                "status": "modified",
                "first_commit": "2011-08-23T18:17:07",
                "last_commit": "2013-08-23T13:46:28",
                "CI_type": "Travis",
                "sha": "e2baf929064ab77e8bedc46582683ce2b471db2f"
            },
            {
                "file_name": "/.travis.yml",
                "commit_date": "2011-08-23T18:17:07",
                "status": "added",
                "first_commit": "2011-08-23T18:17:07",
                "last_commit": "2013-08-23T13:46:28",
                "CI_type": "Travis",
                "sha": "eef546a96452c7e65d694163a6237e7a01a16af6"
            }
        ]
    },
    {
        "CircleCI": []
    },
    {
        "AppVeyor": []
    },
    {
        "Azure": []
    },
    {
        "GitLab": []
    },
    {
        "Jenkins": []
    }
]