{
    "id": 442637163,
    "name": "dde-session",
    "full_name": "linuxdeepin/dde-session",
    "org_name": "Wuhan deepin Technology Co.,Ltd.",
    "org_id": 1592697,
    "created_at": "2021-12-29T02:22:02",
    "pushed_at": "2023-03-01T06:36:06",
    "updated_at": "2021-12-29T13:07:26",
    "isFork": false,
    "forks": 7,
    "forks_count": 7,
    "has_downloads": true,
    "has_issues": true,
    "has_pages": false,
    "has_projects": true,
    "has_wiki": true,
    "homepage": null,
    "language": "C++",
    "open_issues": 1,
    "open_issues_count": 1,
    "size": 261,
    "stargazers_count": 2,
    "subscribers_count": 9,
    "watchers": 2,
    "watchers_count": 2,
    "first_commit": "2022-03-29T03:16:23",
    "last_commit": "2023-02-27T03:21:41",
    "branches_count": 2,
    "commit_comments_count": 0,
    "commits_count": 58,
    "countributors_count": 9,
    "downloads_count": 0,
    "events_count": 53,
    "issues_count": 1,
    "labels_count": 9,
    "milestones_count": 0,
    "PR_count": 6,
    "open_PR_count": 1,
    "readme_size": 1821,
    "release_count": 0,
    "topic_count": 0,
    "15_commits": 0,
    "16_commits": 0,
    "17_commits": 0,
    "18_commits": 0,
    "19_commits": 0,
    "20_commits": 0,
    "21_commits": 0,
    "22_commits": 45,
    "15_committer_num": 0,
    "16_committer_num": 0,
    "17_committer_num": 0,
    "18_committer_num": 0,
    "19_committer_num": 0,
    "20_committer_num": 0,
    "21_committer_num": 0,
    "22_committer_num": 7
}{
    "stargazer_date": {
        "12298476": "2021-12-29T02:27:40",
        "20080233": "2021-12-29T02:42:46"
    }
}[
    {
        "GHA": [
            {
                "file_name": ".github/workflows/backup-to-gitlab.yml",
                "commit_date": "2023-01-12T07:11:07",
                "status": "added",
                "first_commit": "2023-01-12T07:11:07",
                "last_commit": "2023-01-12T07:11:07",
                "CI_type": "GHA",
                "sha": "2d56ed9f4c427a91ff4011000365ec1b31fd912c"
            },
            {
                "file_name": ".github/workflows/call-commitlint.yml",
                "commit_date": "2023-01-12T07:11:07",
                "status": "added",
                "first_commit": "2023-01-12T07:11:07",
                "last_commit": "2023-01-12T07:11:07",
                "CI_type": "GHA",
                "sha": "2d56ed9f4c427a91ff4011000365ec1b31fd912c"
            },
            {
                "file_name": ".github/workflows/call-chatOps.yml",
                "commit_date": "2023-01-12T07:11:07",
                "status": "added",
                "first_commit": "2023-01-12T07:11:07",
                "last_commit": "2023-01-12T07:11:07",
                "CI_type": "GHA",
                "sha": "2d56ed9f4c427a91ff4011000365ec1b31fd912c"
            },
            {
                "file_name": ".github/workflows/call-tag-build.yml",
                "commit_date": "2023-01-12T07:11:07",
                "status": "added",
                "first_commit": "2023-01-12T07:11:07",
                "last_commit": "2023-01-12T07:11:07",
                "CI_type": "GHA",
                "sha": "2d56ed9f4c427a91ff4011000365ec1b31fd912c"
            },
            {
                "file_name": ".github/workflows/call-build-distribution.yml",
                "commit_date": "2023-01-12T07:11:07",
                "status": "added",
                "first_commit": "2023-01-12T07:11:07",
                "last_commit": "2023-01-12T07:11:07",
                "CI_type": "GHA",
                "sha": "2d56ed9f4c427a91ff4011000365ec1b31fd912c"
            },
            {
                "file_name": ".github/workflows/call-license-check.yml",
                "commit_date": "2023-01-12T07:11:07",
                "status": "added",
                "first_commit": "2023-01-12T07:11:07",
                "last_commit": "2023-01-12T07:11:07",
                "CI_type": "GHA",
                "sha": "2d56ed9f4c427a91ff4011000365ec1b31fd912c"
            },
            {
                "file_name": ".github/workflows/call-auto-tag.yml",
                "commit_date": "2023-01-12T07:11:07",
                "status": "added",
                "first_commit": "2023-01-12T07:11:07",
                "last_commit": "2023-01-12T07:11:07",
                "CI_type": "GHA",
                "sha": "2d56ed9f4c427a91ff4011000365ec1b31fd912c"
            },
            {
                "file_name": ".github/workflows/call-clacheck.yml",
                "commit_date": "2023-01-12T07:11:07",
                "status": "added",
                "first_commit": "2023-01-12T07:11:07",
                "last_commit": "2023-01-12T07:11:07",
                "CI_type": "GHA",
                "sha": "2d56ed9f4c427a91ff4011000365ec1b31fd912c"
            }
        ]
    },
    {
        "Travis": []
    },
    {
        "CircleCI": []
    },
    {
        "AppVeyor": []
    },
    {
        "Azure": []
    },
    {
        "GitLab": []
    },
    {
        "Jenkins": []
    }
]